manim_fa/__init__.py
manim_fa/fonts.py
manim_fa/text.py
manim_fa/translit.py
manim_fa-0.3.6.dist-info/licenses/LICENSE
manim_fa-0.3.6.dist-info/METADATA
manim_fa-0.3.6.dist-info/WHEEL
manim_fa-0.3.6.dist-info/top_level.txt
manim_fa-0.3.6.dist-info/RECORD
