Metadata-Version: 2.4
Name: manim-fa
Version: 0.3.6
Summary: افزونه‌ی مانیم برای نمایش متن فارسی (راست به چپ) با قابلیت تبدیل خودکار از حروف لاتین به فارسی
Home-page: https://github.com/Tabesh2020/manim-fa
Author: علی تابش
Author-email: علی تابش <tabesh_ali@yahoo.com>
License: MIT License
Project-URL: Homepage, https://github.com/Tabesh2020/manim-fa
Requires-Python: >=3.8
License-File: LICENSE
Requires-Dist: manim>=0.17.0
Requires-Dist: arabic-reshaper
Requires-Dist: python-bidi
Dynamic: author
Dynamic: home-page
Dynamic: license-file
